LICENSE
MANIFEST.in
README.rst
requirements.txt
setup.cfg
setup.py
versioneer.py
mixpanel_jql/__init__.py
mixpanel_jql/_version.py
mixpanel_jql/exceptions.py
mixpanel_jql/query.py
mixpanel_jql.egg-info/PKG-INFO
mixpanel_jql.egg-info/SOURCES.txt
mixpanel_jql.egg-info/dependency_links.txt
mixpanel_jql.egg-info/requires.txt
mixpanel_jql.egg-info/top_level.txt