Metadata-Version: 1.1
Name: mixpanel-jql
Version: 0.5
Summary: A streaming library for making JQL queries to Mixpanel
Home-page: https://github.com/ownaginatious/mixpanel-jql
Author: Dillon Dixon
Author-email: dillondixon@gmail.com
License: MIT
Keywords: mixpanel,jql,stream
Platform: UNKNOWN
Classifier: License :: OSI Approved :: MIT License
Classifier: Programming Language :: Python :: 2.7
Classifier: Programming Language :: Python :: 3.3
Classifier: Programming Language :: Python :: 3.4
Classifier: Programming Language :: Python :: 3.5
Classifier: Programming Language :: Python :: 3.6
